pynet_scanner/__init__.py
pynet_scanner/scanner.py
tests/__init__.py
tests/test_scanner.py
pynet_scanner-0.1.1.dist-info/LICENSE
pynet_scanner-0.1.1.dist-info/METADATA
pynet_scanner-0.1.1.dist-info/WHEEL
pynet_scanner-0.1.1.dist-info/entry_points.txt
pynet_scanner-0.1.1.dist-info/top_level.txt
pynet_scanner-0.1.1.dist-info/RECORD
