Metadata-Version: 2.1
Name: pynet_scanner
Version: 0.1.1
Summary: A package for discovering clients in a local network.
Home-page: https://gitlab.com/sasansharifipour/network_scanner
Author: Sasan Sharifipour
Author-email: Sasansharifipour@gmail.com
Classifier: Programming Language :: Python :: 3
Classifier: License :: OSI Approved :: MIT License
Classifier: Operating System :: OS Independent
Requires-Python: >=3.6
License-File: LICENSE
